prometheus_redis/__init__.py
prometheus_redis/etc/__init__.py
prometheus_redis/etc/enums.py
prometheus_redis/etc/errors.py
prometheus_redis/models/__init__.py
prometheus_redis/models/collector.py
prometheus_redis/models/metric.py
prometheus_redis/models/registry.py
prometheus_redis-0.1.0.dist-info/LICENSE
prometheus_redis-0.1.0.dist-info/METADATA
prometheus_redis-0.1.0.dist-info/WHEEL
prometheus_redis-0.1.0.dist-info/top_level.txt
prometheus_redis-0.1.0.dist-info/RECORD
