Metadata-Version: 2.1
Name: prometheus_redis
Version: 0.1.0
Summary: A Prometheus client to use Redis as metrics storage.
Author-email: Firefox2100 <wangyunze16@gmail.com>
License: GNU GENERAL PUBLIC LICENSE
Project-URL: Homepage, https://github.com/Firefox2100/prometheus-redis
Project-URL: Issues, https://github.com/Firefox2100/prometheus-redis/issues
Classifier: Development Status :: 4 - Beta
Classifier: Intended Audience :: Developers
Classifier: Programming Language :: Python :: 3
Classifier: Programming Language :: Python :: 3.6
Classifier: License :: OSI Approved :: GNU General Public License v3 (GPLv3)
Classifier: Operating System :: OS Independent
Requires-Python: >=3.8
License-File: LICENSE
Requires-Dist: prometheus-client ==0.20.0
Requires-Dist: redis ==5.0.4
